dsnetserver/__init__.py
dsnetserver/main.py
dsnetserver/models.py
test/__init__.py
test/test_http.py
datashare_network_server-0.7.0.dist-info/LICENSE.txt
datashare_network_server-0.7.0.dist-info/METADATA
datashare_network_server-0.7.0.dist-info/WHEEL
datashare_network_server-0.7.0.dist-info/top_level.txt
datashare_network_server-0.7.0.dist-info/RECORD
