Metadata-Version: 2.1
Name: datashare-network-server
Version: 0.7.0
Summary: Datashare Network Server
Home-page: https://github.com/icij/datashare-network-server
License: UNKNOWN
Keywords: datashare,server,network,cryptography
Platform: UNKNOWN
Classifier: Programming Language :: Python :: 3
Classifier: Programming Language :: Python :: 3.6
Classifier: Programming Language :: Python :: 3.7
Classifier: Programming Language :: Python :: 3.8
Classifier: Intended Audience :: Developers
Classifier: License :: OSI Approved :: GNU Affero General Public License v3
Classifier: Operating System :: OS Independent
Classifier: Topic :: Security :: Cryptography
Requires-Python: >=3.6
License-File: LICENSE.txt
Requires-Dist: alembic
Requires-Dist: databases[postgresql,sqlite]
Requires-Dist: datashare-network-core (==0.13.0)
Requires-Dist: psycopg2
Requires-Dist: pytest
Requires-Dist: sqlalchemy
Requires-Dist: starlette
Requires-Dist: uvicorn[standard]
